BackWard.py
ForWard.py
setup.py
EpistaSim_Linux.egg-info/PKG-INFO
EpistaSim_Linux.egg-info/SOURCES.txt
EpistaSim_Linux.egg-info/dependency_links.txt
EpistaSim_Linux.egg-info/top_level.txt