Metadata-Version: 1.0
Name: EpistaSim-Linux
Version: 1.1.0
Summary:  Simulator of Single nucleotide polymorphism (SNP) patetrn in a region from two loci through forward and coalescent process with mutation and recombination under selection model
Home-page: http://blog.useasp.net/
Author: Shaojun Zhang
Author-email: zhangsahojun@ems.hrbmu.edu.cn
License: MIT
Keywords: epistasis simulation
Platform: UNKNOWN
Classifier: Development Status :: 3 - Alpha
Classifier: Intended Audience :: Science/Research
Classifier: Topic :: Software Development :: Build Tools
Classifier: License :: OSI Approved :: Python Software Foundation License
Classifier: Environment :: Win32 (MS Windows)
Classifier: Operating System :: Unix
Classifier: Programming Language :: Python :: 2.6
Classifier: Programming Language :: Python :: 2.7
